rbtv.py
rbtv_api-0.0.8.dist-info/METADATA
rbtv_api-0.0.8.dist-info/WHEEL
rbtv_api-0.0.8.dist-info/top_level.txt
rbtv_api-0.0.8.dist-info/RECORD
